cpl/__init__.py
cpl/main.py
cpl/metadata.py
cpl-0.1.1.dist-info/DESCRIPTION.rst
cpl-0.1.1.dist-info/METADATA
cpl-0.1.1.dist-info/RECORD
cpl-0.1.1.dist-info/WHEEL
cpl-0.1.1.dist-info/metadata.json
cpl-0.1.1.dist-info/top_level.txt
